LICENSE
README.md
pyproject.toml
django_command/__init__.py
django_command/command.py
django_command.egg-info/PKG-INFO
django_command.egg-info/SOURCES.txt
django_command.egg-info/dependency_links.txt
django_command.egg-info/entry_points.txt
django_command.egg-info/requires.txt
django_command.egg-info/top_level.txt