Metadata-Version: 2.1
Name: django-command
Version: 2.2.0
Summary: Django-command is a command line tool that allows you to run commonly used commands in development Django projects.
Maintainer-email: Isaev Abbas <abbas.isaev@gmail.com>
License: Copyright (c) 2023 Abbas Isaev.
Project-URL: Homepage, https://github.com/AbbasIsaev/django-command
Project-URL: Repository, https://github.com/AbbasIsaev/django-command.git
Keywords: django-command,Django,cli
Classifier: Programming Language :: Python :: 3
Classifier: License :: OSI Approved :: MIT License
Classifier: Operating System :: OS Independent
Requires-Python: >=3.5
License-File: LICENSE
Requires-Dist: inquirer>=3.1.3
